<?xml version = '1.0' encoding = 'UTF-8'?>
<Table class="oracle.dbtools.crest.model.design.relational.Table" directorySegmentName="seg_0" id="672274BC-38A1-C21C-7761-E19A5B0E2A53" name="TBL_NUMEROS_CONSUMIDOR">
<createdBy>steph</createdBy>
<createdTime>2023-10-20 15:26:02 UTC</createdTime>
<ownerDesignName>MODELO_BD_AMAZON</ownerDesignName>
<ordsAlias>table_31</ordsAlias>
<allowColumnReorder>false</allowColumnReorder>
<existDependencyGenerateInDDl>true</existDependencyGenerateInDDl>
<parsed>true</parsed>
</Table>
